napari_listener/__init__.py
napari_listener/_actions.py
napari_listener/_app_model_handler.py
napari_listener/_version.py
napari_listener/_widget.py
napari_listener/napari.yaml
napari_listener/_tests/__init__.py
napari_listener/_tests/test_widget.py
napari_listener-0.1.0b1.post1.dist-info/LICENSE
napari_listener-0.1.0b1.post1.dist-info/METADATA
napari_listener-0.1.0b1.post1.dist-info/WHEEL
napari_listener-0.1.0b1.post1.dist-info/entry_points.txt
napari_listener-0.1.0b1.post1.dist-info/top_level.txt
napari_listener-0.1.0b1.post1.dist-info/RECORD
