Metadata-Version: 2.1
Name: napari-listener
Version: 0.1.0b1.post1
Summary: Control napari via local socket.
Home-page: https://github.com/aganders3/napari-listener
Author: Ashley Anderson
Author-email: aandersoniii@chanzuckerberg.com
License: MIT
Project-URL: Bug Tracker, https://github.com/aganders3/napari-listener/issues
Project-URL: Documentation, https://github.com/aganders3/napari-listener#README.md
Project-URL: Source Code, https://github.com/aganders3/napari-listener
Project-URL: User Support, https://github.com/aganders3/napari-listener/issues
Classifier: Development Status :: 2 - Pre-Alpha
Classifier: Framework :: napari
Classifier: Intended Audience :: Developers
Classifier: License :: OSI Approved :: MIT License
Classifier: Operating System :: OS Independent
Classifier: Programming Language :: Python
Classifier: Programming Language :: Python :: 3
Classifier: Programming Language :: Python :: 3 :: Only
Classifier: Programming Language :: Python :: 3.8
Classifier: Programming Language :: Python :: 3.9
Classifier: Programming Language :: Python :: 3.10
Classifier: Programming Language :: Python :: 3.11
Requires-Python: >=3.8
License-File: LICENSE
Requires-Dist: napari
Requires-Dist: qtpy
Provides-Extra: testing
Requires-Dist: tox ; extra == 'testing'
Requires-Dist: pytest ; extra == 'testing'
Requires-Dist: pytest-cov ; extra == 'testing'
Requires-Dist: pytest-qt ; extra == 'testing'
Requires-Dist: pyqt5 ; extra == 'testing'
